{
    "Cartridge": [
        {
            "count": 20,
            "manufacturer": "HP",
            "name": "26X"
        },
        {
            "count": 4,
            "manufacturer": "HP",
            "name": "78A"
        },
        {
            "count": 4,
            "manufacturer": "HP",
            "name": "83X"
        },
        {
            "count": 2,
            "manufacturer": "HP",
            "name": "85A"
        },
        {
            "count": 5,
            "manufacturer": "HP",
            "name": "81A"
        }
    ],
    "Supply": [
        {
            "cartridge_id": "26X",
            "comment": "",
            "count": 10,
            "date": "2020-05-13T12:53:07.627Z",
            "id": 1,
            "out": true
        },
        {
            "cartridge_id": "26X",
            "comment": "",
            "count": 1,
            "date": "2020-05-13T08:03:11.140Z",
            "id": 2,
            "out": true
        },
        {
            "cartridge_id": "26X",
            "comment": "",
            "count": 1,
            "date": "2020-05-13T08:03:16.897Z",
            "id": 3,
            "out": false
        },
        {
            "cartridge_id": "78A",
            "comment": "",
            "count": 2,
            "date": "2020-05-13T08:03:22.045Z",
            "id": 4,
            "out": true
        },
        {
            "cartridge_id": "78A",
            "comment": "",
            "count": 5,
            "date": "2020-05-13T12:53:37.127Z",
            "id": 5,
            "out": false
        }
    ]
}